{"ISBN:9782070415809":{"weight":"5.6 ounces","authors":[{"url":"http:\/\/openlibrary.org\/authors\/OL22161A\/H.P._Lovecraft","name":"H.P. Lovecraft"}],"identifiers":{"goodreads":["1289628"],"isbn_10":["2070415805"],"openlibrary":["OL8839463M"],"isbn_13":["9782070415809"],"librarything":["295157"]},"title":"La Couleur tombée du ciel","publishers":[{"name":"Gallimard"}],"publish_date":"October 11, 2000","key":"\/books\/OL8839463M","cover":{"small":"https:\/\/covers.openlibrary.org\/b\/id\/968756-S.jpg","large":"https:\/\/covers.openlibrary.org\/b\/id\/968756-L.jpg","medium":"https:\/\/covers.openlibrary.org\/b\/id\/968756-M.jpg"},"number_of_pages":332,"url":"http:\/\/openlibrary.org\/books\/OL8839463M\/La_Couleur_tombée_du_ciel"}}
{"ISBN:9782070415809":{"weight":"5.6 ounces","authors":[{"url":"http:\/\/openlibrary.org\/authors\/OL22161A\/H.P._Lovecraft","name":"H.P. Lovecraft"}],"identifiers":{"goodreads":["1289628"],"isbn_10":["2070415805"],"openlibrary":["OL8839463M"],"isbn_13":["9782070415809"],"librarything":["295157"]},"title":"La Couleur tombée du ciel","publishers":[{"name":"Gallimard"}],"publish_date":"October 11, 2000","key":"\/books\/OL8839463M","cover":{"small":"https:\/\/covers.openlibrary.org\/b\/id\/968756-S.jpg","large":"https:\/\/covers.openlibrary.org\/b\/id\/968756-L.jpg","medium":"https:\/\/covers.openlibrary.org\/b\/id\/968756-M.jpg"},"number_of_pages":332,"url":"http:\/\/openlibrary.org\/books\/OL8839463M\/La_Couleur_tombée_du_ciel"}}
{"ISBN:9782070415809":{"weight":"5.6 ounces","authors":[{"url":"http:\/\/openlibrary.org\/authors\/OL22161A\/H.P._Lovecraft","name":"H.P. Lovecraft"}],"identifiers":{"goodreads":["1289628"],"isbn_10":["2070415805"],"openlibrary":["OL8839463M"],"isbn_13":["9782070415809"],"librarything":["295157"]},"title":"La Couleur tombée du ciel","publishers":[{"name":"Gallimard"}],"publish_date":"October 11, 2000","key":"\/books\/OL8839463M","cover":{"small":"https:\/\/covers.openlibrary.org\/b\/id\/968756-S.jpg","large":"https:\/\/covers.openlibrary.org\/b\/id\/968756-L.jpg","medium":"https:\/\/covers.openlibrary.org\/b\/id\/968756-M.jpg"},"number_of_pages":332,"url":"http:\/\/openlibrary.org\/books\/OL8839463M\/La_Couleur_tombée_du_ciel"}}
{"ISBN:9782070426065":{"subjects":[{"name":"American Science fiction","url":"https:\/\/openlibrary.org\/subjects\/american_science_fiction"},{"name":"Fiction, science fiction, general","url":"https:\/\/openlibrary.org\/subjects\/fiction,_science_fiction,_general"},{"name":"Crime prevention","url":"https:\/\/openlibrary.org\/subjects\/crime_prevention"},{"name":"Fiction","url":"https:\/\/openlibrary.org\/subjects\/fiction"},{"name":"Science Fiction","url":"https:\/\/openlibrary.org\/subjects\/science_fiction"},{"name":"American Short stories","url":"https:\/\/openlibrary.org\/subjects\/american_short_stories"}],"authors":[{"url":"http:\/\/openlibrary.org\/authors\/OL274606A\/Philip_K._Dick","name":"Philip K. Dick"},{"url":"http:\/\/openlibrary.org\/authors\/OL3113922A\/Hélène_Collon","name":"Hélène Collon"}],"identifiers":{"isbn_10":["2070426068"],"openlibrary":["OL27264315M"],"amazon":["2070426068"],"isbn_13":["9782070426065"]},"title":"Minority Report","publishers":[{"name":"Gallimard"}],"publish_date":"Oct 02, 2002","key":"\/books\/OL27264315M","excerpts":[{"comment":"","text":"TENSION hung over the three waiting men.","first_sentence":true},{"comment":"","text":"TENSION hung over the three waiting men."},{"comment":"","text":"TENSION hung over the three waiting men."}],"cover":{"small":"https:\/\/covers.openlibrary.org\/b\/id\/8753554-S.jpg","large":"https:\/\/covers.openlibrary.org\/b\/id\/8753554-L.jpg","medium":"https:\/\/covers.openlibrary.org\/b\/id\/8753554-M.jpg"},"url":"http:\/\/openlibrary.org\/books\/OL27264315M\/Minority_Report"}}
